django_shortcircuit-0.1.0.dist-info/DESCRIPTION.rst
django_shortcircuit-0.1.0.dist-info/METADATA
django_shortcircuit-0.1.0.dist-info/RECORD
django_shortcircuit-0.1.0.dist-info/WHEEL
django_shortcircuit-0.1.0.dist-info/metadata.json
django_shortcircuit-0.1.0.dist-info/pbr.json
django_shortcircuit-0.1.0.dist-info/top_level.txt
shortcircuit/__init__.py
shortcircuit/middleware.py
shortcircuit/models.py
shortcircuit/static/css/shortcircuit.css
shortcircuit/static/js/shortcircuit.js
shortcircuit/templates/shortcircuit/base.html
