Metadata-Version: 1.1
Name: django-shortcircuit
Version: 0.1.0
Summary: Shortcircuit Django middlewares for a list of views you want skipped
Home-page: https://github.com/comandrei/django-shortcircuit
Author: Andrei Coman
Author-email: comandrei@gmail.com
License: BSD
Keywords: django-shortcircuit
Platform: UNKNOWN
Classifier: Development Status :: 3 - Alpha
Classifier: Framework :: Django
Classifier: Framework :: Django :: 1.7
Classifier: Framework :: Django :: 1.8
Classifier: Framework :: Django :: 1.9
Classifier: Intended Audience :: Developers
Classifier: License :: OSI Approved :: BSD License
Classifier: Natural Language :: English
Classifier: Programming Language :: Python :: 2
Classifier: Programming Language :: Python :: 2.7
Classifier: Programming Language :: Python :: 3
Classifier: Programming Language :: Python :: 3.3
Classifier: Programming Language :: Python :: 3.4
Classifier: Programming Language :: Python :: 3.5
